decorator_utils/__init__.py
decorator_utils/context.py
decorator_utils/metadata.py
decorator_utils/wrapper.py
decorator_utils/decorators/__init__.py
decorator_utils/decorators/benchmark.py
decorator_utils-1.1.1.dist-info/METADATA
decorator_utils-1.1.1.dist-info/WHEEL
decorator_utils-1.1.1.dist-info/licenses/LICENSE
decorator_utils-1.1.1.dist-info/RECORD
