Metadata-Version: 2.3
Name: decorator-utils
Version: 1.1.1
Summary: Simple and useful decorator utilities.
Project-URL: Repository, https://github.com/stickm4n/decorator-utils
Project-URL: Documentation, https://github.com/stickm4n/decorator-utils/wiki
Project-URL: Issues, https://github.com/stickm4n/decorator-utils/issues
Author-email: "Julio C. Galindo" <jcgalindo.jcgh@gmail.com>
License: MIT License
License-File: LICENSE
Keywords: decorator,utilities
Classifier: Development Status :: 5 - Production/Stable
Classifier: Intended Audience :: Developers
Classifier: License :: OSI Approved :: MIT License
Classifier: Operating System :: OS Independent
Classifier: Programming Language :: Python :: 3
Classifier: Programming Language :: Python :: 3.9
Classifier: Programming Language :: Python :: 3.10
Classifier: Programming Language :: Python :: 3.11
Classifier: Programming Language :: Python :: 3.12
Classifier: Programming Language :: Python :: 3.13
Requires-Python: >=3.9
